{
  "best_metric": 0.33349999999999996,
  "best_model_checkpoint": "./model/checkpoint-420",
  "epoch": 6.271698113207547,
  "eval_steps": 20,
  "global_step": 420,
  "is_hyper_param_search": false,
  "is_local_process_zero": true,
  "is_world_process_zero": true,
  "log_history": [
    {
      "epoch": 0.3018867924528302,
      "eval_loss": 5.264680862426758,
      "eval_runtime": 41.3464,
      "eval_samples_per_second": 2.419,
      "eval_socratic_style": 0.1525,
      "eval_steps_per_second": 1.209,
      "step": 20
    },
    {
      "epoch": 0.6037735849056604,
      "eval_loss": 4.644312858581543,
      "eval_runtime": 45.0373,
      "eval_samples_per_second": 2.22,
      "eval_socratic_style": 0.1525,
      "eval_steps_per_second": 1.11,
      "step": 40
    },
    {
      "epoch": 0.7547169811320755,
      "grad_norm": 5.130895614624023,
      "learning_rate": 8.08080808080808e-06,
      "loss": 4.923,
      "step": 50
    },
    {
      "epoch": 0.9056603773584906,
      "eval_loss": 3.747187614440918,
      "eval_runtime": 39.8773,
      "eval_samples_per_second": 2.508,
      "eval_socratic_style": 0.0885,
      "eval_steps_per_second": 1.254,
      "step": 60
    },
    {
      "epoch": 1.1962264150943396,
      "eval_loss": 3.0645861625671387,
      "eval_runtime": 40.0962,
      "eval_samples_per_second": 2.494,
      "eval_socratic_style": 0.086,
      "eval_steps_per_second": 1.247,
      "step": 80
    },
    {
      "epoch": 1.4981132075471697,
      "grad_norm": 1.9010002613067627,
      "learning_rate": 1.616161616161616e-05,
      "loss": 3.2403,
      "step": 100
    },
    {
      "epoch": 1.4981132075471697,
      "eval_loss": 2.5695669651031494,
      "eval_runtime": 39.8829,
      "eval_samples_per_second": 2.507,
      "eval_socratic_style": 0.15699999999999997,
      "eval_steps_per_second": 1.254,
      "step": 100
    },
    {
      "epoch": 1.8,
      "eval_loss": 2.3247523307800293,
      "eval_runtime": 39.7581,
      "eval_samples_per_second": 2.515,
      "eval_socratic_style": 0.2619999999999999,
      "eval_steps_per_second": 1.258,
      "step": 120
    },
    {
      "epoch": 2.090566037735849,
      "eval_loss": 2.1932623386383057,
      "eval_runtime": 40.3307,
      "eval_samples_per_second": 2.48,
      "eval_socratic_style": 0.2729999999999999,
      "eval_steps_per_second": 1.24,
      "step": 140
    },
    {
      "epoch": 2.241509433962264,
      "grad_norm": 1.25542414188385,
      "learning_rate": 2.4242424242424244e-05,
      "loss": 2.2963,
      "step": 150
    },
    {
      "epoch": 2.392452830188679,
      "eval_loss": 2.1138949394226074,
      "eval_runtime": 39.4277,
      "eval_samples_per_second": 2.536,
      "eval_socratic_style": 0.26699999999999996,
      "eval_steps_per_second": 1.268,
      "step": 160
    },
    {
      "epoch": 2.6943396226415093,
      "eval_loss": 2.0511176586151123,
      "eval_runtime": 39.8159,
      "eval_samples_per_second": 2.512,
      "eval_socratic_style": 0.2854999999999999,
      "eval_steps_per_second": 1.256,
      "step": 180
    },
    {
      "epoch": 2.9962264150943394,
      "grad_norm": 1.3817789554595947,
      "learning_rate": 3.232323232323232e-05,
      "loss": 2.0517,
      "step": 200
    },
    {
      "epoch": 2.9962264150943394,
      "eval_loss": 2.0051255226135254,
      "eval_runtime": 40.3379,
      "eval_samples_per_second": 2.479,
      "eval_socratic_style": 0.2899999999999999,
      "eval_steps_per_second": 1.24,
      "step": 200
    },
    {
      "epoch": 3.2867924528301886,
      "eval_loss": 1.973332405090332,
      "eval_runtime": 40.1432,
      "eval_samples_per_second": 2.491,
      "eval_socratic_style": 0.30049999999999993,
      "eval_steps_per_second": 1.246,
      "step": 220
    },
    {
      "epoch": 3.5886792452830187,
      "eval_loss": 1.9450417757034302,
      "eval_runtime": 39.5822,
      "eval_samples_per_second": 2.526,
      "eval_socratic_style": 0.26349999999999996,
      "eval_steps_per_second": 1.263,
      "step": 240
    },
    {
      "epoch": 3.739622641509434,
      "grad_norm": 1.369665503501892,
      "learning_rate": 4.040404040404041e-05,
      "loss": 1.9334,
      "step": 250
    },
    {
      "epoch": 3.890566037735849,
      "eval_loss": 1.9232521057128906,
      "eval_runtime": 39.5799,
      "eval_samples_per_second": 2.527,
      "eval_socratic_style": 0.29899999999999993,
      "eval_steps_per_second": 1.263,
      "step": 260
    },
    {
      "epoch": 4.181132075471698,
      "eval_loss": 1.9127758741378784,
      "eval_runtime": 39.9771,
      "eval_samples_per_second": 2.501,
      "eval_socratic_style": 0.2864999999999999,
      "eval_steps_per_second": 1.251,
      "step": 280
    },
    {
      "epoch": 4.483018867924528,
      "grad_norm": 1.8340288400650024,
      "learning_rate": 4.848484848484849e-05,
      "loss": 1.8712,
      "step": 300
    },
    {
      "epoch": 4.483018867924528,
      "eval_loss": 1.8973842859268188,
      "eval_runtime": 40.4132,
      "eval_samples_per_second": 2.474,
      "eval_socratic_style": 0.2834999999999999,
      "eval_steps_per_second": 1.237,
      "step": 300
    },
    {
      "epoch": 4.784905660377358,
      "eval_loss": 1.8847718238830566,
      "eval_runtime": 39.6297,
      "eval_samples_per_second": 2.523,
      "eval_socratic_style": 0.26249999999999996,
      "eval_steps_per_second": 1.262,
      "step": 320
    },
    {
      "epoch": 5.0754716981132075,
      "eval_loss": 1.8701153993606567,
      "eval_runtime": 39.7307,
      "eval_samples_per_second": 2.517,
      "eval_socratic_style": 0.30649999999999994,
      "eval_steps_per_second": 1.258,
      "step": 340
    },
    {
      "epoch": 5.226415094339623,
      "grad_norm": 1.7134418487548828,
      "learning_rate": 5.656565656565657e-05,
      "loss": 1.8286,
      "step": 350
    },
    {
      "epoch": 5.377358490566038,
      "eval_loss": 1.855452299118042,
      "eval_runtime": 39.6704,
      "eval_samples_per_second": 2.521,
      "eval_socratic_style": 0.29599999999999993,
      "eval_steps_per_second": 1.26,
      "step": 360
    },
    {
      "epoch": 5.679245283018868,
      "eval_loss": 1.845271348953247,
      "eval_runtime": 39.3154,
      "eval_samples_per_second": 2.544,
      "eval_socratic_style": 0.2529999999999999,
      "eval_steps_per_second": 1.272,
      "step": 380
    },
    {
      "epoch": 5.981132075471698,
      "grad_norm": 2.1119751930236816,
      "learning_rate": 6.464646464646465e-05,
      "loss": 1.7781,
      "step": 400
    },
    {
      "epoch": 5.981132075471698,
      "eval_loss": 1.8342688083648682,
      "eval_runtime": 39.4278,
      "eval_samples_per_second": 2.536,
      "eval_socratic_style": 0.24899999999999992,
      "eval_steps_per_second": 1.268,
      "step": 400
    },
    {
      "epoch": 6.271698113207547,
      "eval_loss": 1.8263843059539795,
      "eval_runtime": 39.978,
      "eval_samples_per_second": 2.501,
      "eval_socratic_style": 0.33349999999999996,
      "eval_steps_per_second": 1.251,
      "step": 420
    }
  ],
  "logging_steps": 50,
  "max_steps": 1980,
  "num_input_tokens_seen": 0,
  "num_train_epochs": 30,
  "save_steps": 20,
  "stateful_callbacks": {
    "TrainerControl": {
      "args": {
        "should_epoch_stop": false,
        "should_evaluate": false,
        "should_log": false,
        "should_save": true,
        "should_training_stop": false
      },
      "attributes": {}
    }
  },
  "total_flos": 4.143909457310515e+16,
  "train_batch_size": 4,
  "trial_name": null,
  "trial_params": null
}
